toparu/ATB.py
toparu/__init__.py
toparu_arushigupta-0.0.2.dist-info/LICENSE
toparu_arushigupta-0.0.2.dist-info/METADATA
toparu_arushigupta-0.0.2.dist-info/WHEEL
toparu_arushigupta-0.0.2.dist-info/top_level.txt
toparu_arushigupta-0.0.2.dist-info/RECORD
