Metadata-Version: 2.1
Name: toparu-arushigupta
Version: 0.0.2
Summary: A small package that showcases topsis approach
Home-page: https://github.com/user/reponame/archive/v_01.tar.gz
Author: Arushi Gupta
Author-email: agupta11_be17@thapar.edu
License: UNKNOWN
Platform: UNKNOWN
Classifier: Programming Language :: Python :: 3
Classifier: License :: OSI Approved :: MIT License
Classifier: Operating System :: OS Independent
Requires-Python: >=3.6
